{
	"name": "SourceDataset_nc1",
	"properties": {
		"linkedServiceName": {
			"referenceName": "AzureDataLakeStorage1",
			"type": "LinkedServiceReference"
		},
		"annotations": [],
		"type": "DelimitedText",
		"typeProperties": {
			"location": {
				"type": "AzureBlobFSLocation",
				"fileName": "new 14.txt",
				"folderPath": "In",
				"fileSystem": "cstdwhdlfs"
			},
			"columnDelimiter": ";",
			"escapeChar": "\\",
			"firstRowAsHeader": false,
			"quoteChar": "\""
		},
		"schema": [
			{
				"type": "String"
			},
			{
				"type": "String"
			},
			{
				"type": "String"
			}
		]
	},
	"type": "Microsoft.Synapse/workspaces/datasets"
}